[
  {
    "question": "Допускается ли оставлять вентили баллонов в открытом состоянии при транспортировке, перерыве в работе, по завершению работ и после опорожнения баллонов?",
    "options": [
      "Запрещается.",
      "Разрешается.",
      "Допускается в аварийной ситуации."
    ],
    "correct": 0
  },
  {
    "question": "Для чего проводится одоризация пропан бутановых смесей?",
    "options": [
      "Для придания горючему газу запаха с целью быстрого обнаружения при утечках.",
      "Для увеличения калорийности топлива.",
      "Для уменьшения удельного веса."
    ],
    "correct": 0
  },
  {
    "question": "В каких случаях запрещается применение рукавов (шлангов) для сварки металла?",
    "options": [
      "Рукавов для кислорода вместо рукавов для ацетилена.",
      "Рукавов для ацетилена вместо рукавов для кислорода.",
      "Дефектных, негерметичных рукавов.",
      "Во всех случаях, перечисленных в п.п. 1, 2, 3."
    ],
    "correct": 3
  },
  {
    "question": "Для чего предназначен колпак у баллона?",
    "options": [
      "Для предотвращения утечки газа.",
      "Для устойчивости баллона.",
      "Для защиты вентиля от повреждения.",
      "Для всех вышеуказанных случаев."
    ],
    "correct": 2
  },
  {
    "question": "Расстояние между шкафами с кислородом и горючими газами должно быть:",
    "options": [
      "Не менее 0,15 м.",
      "Не ограничивается.",
      "Не менее 1,5 м."
    ],
    "correct": 0
  },
  {
    "question": "В какой цвет окрашивают баллон с гелием.",
    "options": [
      "В желтый цвет с красной надписью.",
      "В красный цвет с белой надписью.",
      "В зелёный цвет с красной надписью.",
      "В коричневый цвет с белой надписью."
    ],
    "correct": 3
  },
  {
    "question": "Разрешается ли перевозка кислородных баллонов в кузове с промасленными материалами?",
    "options": [
      "Разрешается при обязательной их маркировке.",
      "Не разрешается.",
      "Разрешается по устному распоряжению мастера."
    ],
    "correct": 1
  },
  {
    "question": "Крепление баллонов с горючими газами осуществляется:",
    "options": [
      "Из не искрящего материала.",
      "При помощи деревянных креплений.",
      "Любым способом."
    ],
    "correct": 0
  },
  {
    "question": "В какой цвет окрашивают ацетиленовые баллоны?",
    "options": [
      "Красный, надпись белая.",
      "Голубой, надпись черная.",
      "Белый, надпись красная.",
      "Черный, надпись белая."
    ],
    "correct": 2
  },
  {
    "question": "С какой периодичностью проводится метрологическая поверка манометров?",
    "options": [
      "2 раза в год.",
      "1 раз в квартал.",
      "1 раз в год.",
      "1 раз в 3 года."
    ],
    "correct": 2
  },
  {
    "question": "Допускается ли транспортировка баллонов без навернутых колпаков?",
    "options": [
      "Допускается временно.",
      "Допускается внутри помещений.",
      "Не допускается"
    ],
    "correct": 2
  },
  {
    "question": "Укажите физические свойства аммиака.",
    "options": [
      "В нормальных условиях газ, без запаха, тяжелее воздуха.",
      "В нормальных условиях бесцветный газ с резким запахом, легче воздуха.",
      "В нормальных условиях жидкость с резким запахом."
    ],
    "correct": 1
  },
  {
    "question": "Как правильно перемещать баллоны внутри помещения?",
    "options": [
      "На руках.",
      "На специальных носилках или кантовать в слегка наклонном положении.",
      "На плечах.",
      "Перекатывать в горизонтальном положении."
    ],
    "correct": 1
  },
  {
    "question": "Какие данные должны быть нанесены на верхней сферической части каждого баллона?",
    "options": [
      "Сведения изготовителя, подлежащие нанесению в соответствии с требованиями ТР ТС 032/2013.",
      "Сведения о проведенном техническом освидетельствовании баллона, дата проведения, клеймо организации, проводившей техническое освидетельствование, максимальное разрешенное давление, масса пустого баллона.",
      "Верно все вышеперечисленное."
    ],
    "correct": 2
  },
  {
    "question": "Надписи на баллонах наносят по окружности на длину не менее:",
    "options": [
      "1/3 окружности.",
      "1/2 окружности.",
      "Нет правильного ответа."
    ],
    "correct": 0
  },
  {
    "question": "Какие предупредительные надписи должны быть на шкафах для хранения баллонов?",
    "options": [
      "«Кислород маслоопасно»   чёрным цветом.",
      "«Ацетилен огнеопасно»   белым цветом.",
      "«Пропан огнеопасно»   красным цветом.",
      "Верно все вышеперечисленное."
    ],
    "correct": 3
  },
  {
    "question": "Где следует хранить рукава?",
    "options": [
      "В специальных шкафах.",
      "На специальных вешалках в отведённых для этих целей местах.",
      "В любых местах.",
      "На раме газосварочного поста."
    ],
    "correct": 1
  },
  {
    "question": "Каким образом регламентируется срок службы баллонов?",
    "options": [
      "Срок службы баллонов определяет организация изготовитель.",
      "При отсутствии таких сведений срок службы баллона устанавливают 20 лет.",
      "Правильные ответы в п. 1 и 2."
    ],
    "correct": 2
  },
  {
    "question": "Допускается ли перевозка баллонов в кузове без прокладок между рядами баллонов?",
    "options": [
      "Не допускается.",
      "Допускается.",
      "Допускается только в пределах общезаводской территории."
    ],
    "correct": 0
  },
  {
    "question": "Как оформляются результаты технического освидетельствования баллонов до 100 л включительно?",
    "options": [
      "Краской на корпусе.",
      "Нанесением клейм на верхней сферической части баллона.",
      "В паспорте баллона.",
      "Любым вышеуказанным способом."
    ],
    "correct": 1
  },
  {
    "question": "Что применяется в качестве растворителя в ацетиленовом баллоне?",
    "options": [
      "Вода.",
      "Аммиак.",
      "Ацетон.",
      "Углекислый газ"
    ],
    "correct": 2
  },
  {
    "question": "Какую резьбу должен иметь боковой штуцер вентиля для баллонов с негорючими газами?",
    "options": [
      "Правую.",
      "Левую."
    ],
    "correct": 0
  },
  {
    "question": "Сколько рядов баллонов разрешается укладывать в кузове?",
    "options": [
      "Не более 2-х рядов.",
      "Не более 3-х рядов.",
      "Не более 4-х рядов.",
      "В пределах высоты бортов."
    ],
    "correct": 3
  },
  {
    "question": "В каком положении должны находиться баллоны с ацетиленом и сжиженным газом при эксплуатации?",
    "options": [
      "В горизонтальном.",
      "В слегка наклонном.",
      "В вертикальном."
    ],
    "correct": 2
  },
  {
    "question": "Разрешается ли отбирать газ из баллона без редуктора, предназначенного для снижения давления?",
    "options": [
      "Разрешается.",
      "Допускается в случае обязательного использования водяного затвора.",
      "Запрещается.",
      "Правильный ответ в пунктах 1, 2."
    ],
    "correct": 2
  },
  {
    "question": "Разрешается ли переносить баллоны внутри помещения на руках?",
    "options": [
      "Разрешается только вдвоём.",
      "Разрешается переносить на плечах.",
      "Запрещается.",
      "Разрешается только пустые баллоны."
    ],
    "correct": 2
  },
  {
    "question": "На каком расстоянии должны находиться баллоны с газом от",
    "options": [
      "Не менее 1 м.",
      "Не менее 2 м.",
      "Не менее 3 м.",
      "Не менее 5 м."
    ],
    "correct": 3
  },
  {
    "question": "Срок службы баллонов определяет организация-изготовитель. При отсутствии таких сведений срок службы баллона устанавливают:",
    "options": [
      "20 лет",
      "40 лет",
      "5 лет."
    ],
    "correct": 0
  },
  {
    "question": "Какую резьбу должен иметь боковой штуцер вентиля для баллона, наполненного  водородом:",
    "options": [
      "Правую резьбу.",
      "Левую резьбу."
    ],
    "correct": 1
  },
  {
    "question": "Какую резьбу должен иметь боковой штуцер вентиля для баллона, наполненный   кислородом и другими негорючими газами?",
    "options": [
      "Правую резьбу.",
      "Левую резьбу."
    ],
    "correct": 0
  },
  {
    "question": "Где наносятся паспортные данные на баллоне?",
    "options": [
      "На днище баллона.",
      "На колпаке.",
      "На верхней сферической части баллона.",
      "На корпусе баллона."
    ],
    "correct": 2
  },
  {
    "question": "Каким газом необходимо продуть новые рукава перед применением.",
    "options": [
      "Для горючих газов инертным газом, для кислорода – кислородом, воздухом, азотом, не содержащим следов масла.",
      "Для горючих газов -  кислородом воздухом, азотом, не содержащим следов масла, для кислорода – инертным газом.",
      "Продувать только кислородные рукава с разрешения ответственного.",
      "Запрещается."
    ],
    "correct": 0
  },
  {
    "question": "Перевозка наполненных газом баллонов должна производиться:",
    "options": [
      "На грузовом транспорте или пикапах в горизонтальном положении.",
      "Баллоны укладываются с предохранением от перемещения.",
      "В пикапах баллоны укладываются вдоль кузова в один ряд.",
      "Предохранительные колпаки должны быть направлены в одну сторону.",
      "Верно все перечисленное."
    ],
    "correct": 4
  },
  {
    "question": "Укажите физико химические свойства углекислого газа?",
    "options": [
      "В нормальных условиях газ, без запаха и цвета, тяжелее воздуха, со слегка кисловатым вкусом, не поддерживает горение.",
      "В нормальных условиях бесцветный газ с резким запахом, легче воздуха.",
      "Газ желто зеленого цвета, ядовит."
    ],
    "correct": 0
  },
  {
    "question": "Где должен находиться торцевой ключ для открывания вентиля ацетиленового баллона во время отбора газа из баллона?",
    "options": [
      "У мастера в специальном шкафу.",
      "На шпинделе вентиля баллона.",
      "На рабочем месте"
    ],
    "correct": 1
  },
  {
    "question": "Чем допускается прокладывать ряды баллонов в кузове автомобиля?",
    "options": [
      "Деревянными подкладками с гнёздами.",
      "Резиновыми кольцами.",
      "Канатами толщиной не менее 25 мм.",
      "Всем перечисленными выше материалами."
    ],
    "correct": 3
  },
  {
    "question": "Перед  допуском к  самостоятельной работе по транспортировке газовых баллонов рабочие должны пройти стажировку на рабочем месте в течении:",
    "options": [
      "10 рабочих смен.",
      "5 дней, под руководством мастера.",
      "12 рабочих смен."
    ],
    "correct": 0
  },
  {
    "question": "Чем должен быть укомплектован грузовой автомобиль общего назначения, предназначенный для транспортировки баллонов?",
    "options": [
      "Один огнетушитель, содержащий вещества инертные по отношению к перевозимому грузу.",
      "Один огнетушитель для тушения пожара в двигателе.",
      "Проблесковый маячок оранжевого цвета.",
      "Все ответы правильные."
    ],
    "correct": 3
  },
  {
    "question": "При укладке баллонов в штабеля, высота последних не должна  превышать?",
    "options": [
      "1,5 м.",
      "0,5 м.",
      "Не допускается укладывать  баллоны в штабеля."
    ],
    "correct": 0
  },
  {
    "question": "В какой цвет окрашивают баллон с водородом?",
    "options": [
      "В тёмно-зелёный цвет с красной надписью.",
      "В красный цвет с белой надписью.",
      "В коричневый цвет с белой надписью.",
      "В желтый цвет с красной надписью."
    ],
    "correct": 0
  },
  {
    "question": "Что должен предпринять персонал, перемещающий (транспортирующий)  баллоны при утечке газа из баллона?",
    "options": [
      "Окриком предупредить об опасности всех находящихся поблизости людей, сообщить непосредственному руководителю.",
      "Перекрыть вентили на баллоне, навернуть колпак и отставить баллон в безопасное место, исключающее попадания случайных искр, нанести на отбракованный баллон меловую надпись: \"Осторожно! Утечка! Возврат».",
      "Вызвать транспортное спец. средство для эвакуации баллона с утечкой, обеспечить погрузку и оправку баллона на склад.",
      "Правильный ответ 1, 2.",
      "Все ответы правильные."
    ],
    "correct": 3
  },
  {
    "question": "Избыточное (остаточное) давление газа в баллоне после",
    "options": [
      "Не более 0,5 кгс/см2",
      "Не менее 0,5 кгс/см2, если иное не предусмотрено техническими условиями на газ.",
      "Не более 1 атм.",
      "Не менее 1 атм."
    ],
    "correct": 1
  },
  {
    "question": "Высота укладки баллонов в кузове?",
    "options": [
      "Не более 2 х рядов.",
      "Не более 5 х рядов.",
      "Не более 4 х рядов.",
      "В пределах высоты бортов."
    ],
    "correct": 3
  },
  {
    "question": "Где разрешается размещать склады для хранения баллонов?",
    "options": [
      "В подвальных помещениях.",
      "На чердаках бытовых зданий.",
      "В одноэтажных зданиях.",
      "Правильный ответ 1, 2, 3."
    ],
    "correct": 2
  },
  {
    "question": "Каким требованиям должно отвечать здание склада для хранения баллонов?",
    "options": [
      "Должно быть одноэтажным, с покрытиями легкого типа, без чердачных помещений.",
      "Стены, перегородки, покрытия склада должны быть из несгораемых материалов.",
      "Полы должны быть ровные с нескользкой поверхностью.",
      "Оконные стекла должны быть матовые или закрашены белой краской.",
      "Правильные ответы в п. 1, 2, 3 и 4."
    ],
    "correct": 4
  },
  {
    "question": "Размещение баллонов при эксплуатации.",
    "options": [
      "Не закрепляются.",
      "Под углом 45 градусов",
      "Должны быть закреплены в стойке или на тележке.",
      "Требования отсутствуют."
    ],
    "correct": 2
  },
  {
    "question": "Разрешается ли хранить баллоны на открытом воздухе?",
    "options": [
      "Разрешается, если они защищены от атмосферных осадков и солнечных лучей.",
      "Запрещается.",
      "Разрешается не более 10 штук.",
      "Разрешается не более 3 дней."
    ],
    "correct": 0
  },
  {
    "question": "Разрешается ли разборка и ремонт вентилей баллонов на рабочем месте?",
    "options": [
      "Запрещается.",
      "Разрешается.",
      "Разрешается с соблюдением предосторожности.",
      "Разрешается по наряду-допуску"
    ],
    "correct": 0
  },
  {
    "question": "В какой цвет должна быть окрашена наружная поверхность кислородного баллона?",
    "options": [
      "В голубой цвет с черной надписью.",
      "В белый цвет с красной надписью.",
      "В красный цвет."
    ],
    "correct": 0
  },
  {
    "question": "Периодичность проведения учебно тренировочных занятий по ПМЛА.",
    "options": [
      "Не реже 1 раза в 12 месяцев.",
      "Не реже 1 раза в 3 месяца.",
      "Не реже 2 раз в год по каждой теме.",
      "Не реже 1 раза в неделю."
    ],
    "correct": 2
  },
  {
    "question": "Расстояние от баллонов до радиаторов отопления должно быть:",
    "options": [
      "Не менее 1 м.",
      "Не более 5 м.",
      "Не более 3 м.",
      "Не менее 0,5 м."
    ],
    "correct": 0
  },
  {
    "question": "Допускается ли складское хранение в одном помещении баллонов с кислородом и горючими газами.",
    "options": [
      "Допускается.",
      "Не допускается",
      "Допускается если помещение расположено на открытом воздухе."
    ],
    "correct": 1
  },
  {
    "question": "Какие сведения должны быть на таблицах  расположенных впереди и сзади грузового автомобиля общего назначения, предназначенного для транспортировки баллонов?",
    "options": [
      "Сведения о наличии разрешения от Ростехнадзора на перевозку баллонов.",
      "Даты проведенного и следующего технического освидетельствования.",
      "Сведения о характере опасного груза.",
      "Правильные ответы в п. 1 и 2."
    ],
    "correct": 2
  },
  {
    "question": "Действие жидкого кислорода при попадании на кожу.",
    "options": [
      "Безвреден.",
      "Вызывает обморожение.",
      "Отравление происходит через кожу.",
      "Нет правильного ответа."
    ],
    "correct": 1
  },
  {
    "question": "Чему равно рабочее давление в ацетиленовом баллоне?",
    "options": [
      "200 кгс/см2",
      "150 кгс/см2",
      "19 кгс/см2"
    ],
    "correct": 2
  },
  {
    "question": "Чему равно рабочее давление в баллоне с пропаном?",
    "options": [
      "16 кгс/см2",
      "150 кгс/см2",
      "200 кгс/см2"
    ],
    "correct": 0
  },
  {
    "question": "В какой цвет окрашивают пропановый баллон.",
    "options": [
      "В белый цвет с красной надписью.",
      "В красный цвет с белой надписью.",
      "В зелёный цвет с красной надписью.",
      "В голубой цвет с чёрной надписью."
    ],
    "correct": 1
  },
  {
    "question": "Как приводится в негодность забракованный баллон?",
    "options": [
      "Нанесением насечек на резьбе горловины.",
      "Просверливанием отверстий на корпусе.",
      "Делается надпись «брак» мелом на корпусе.",
      "Правильный ответ в п. 1 и 2."
    ],
    "correct": 3
  },
  {
    "question": "Разрешается ли перевозка наполненных и порожних кислородных баллонов в одном кузове?",
    "options": [
      "Запрещается.",
      "Разрешается при обязательной маркировке.",
      "Разрешается в сумме не более 10."
    ],
    "correct": 1
  },
  {
    "question": "Где должны храниться баллоны по окончании работы?",
    "options": [
      "На рабочих местах.",
      "В специально отведенном месте.",
      "Рекомендуется размещать баллоны в металлических шкафах.",
      "Правильные ответы в п. 2, 3."
    ],
    "correct": 3
  },
  {
    "question": "В складах должны быть вывешены:",
    "options": [
      "Приказы о назначении ответственных.",
      "Инструкции, правила и плакаты по обращению с баллонами.",
      "Список ответственных лиц, занятых эксплуатацией баллонов."
    ],
    "correct": 1
  },
  {
    "question": "Что необходимо сделать, если при приемке баллонов будут выявлены дефекты?",
    "options": [
      "Произвести ремонт.",
      "Возвратить на наполнительную станцию с составлением акта.",
      "Использовать с разрешения ответственного."
    ],
    "correct": 1
  },
  {
    "question": "Чему равно рабочее давление в кислородном баллоне?",
    "options": [
      "150 кгс/см2",
      "19 кгс/см2",
      "20 кгс/см2"
    ],
    "correct": 0
  },
  {
    "question": "Укажите места вероятного скопления кислорода при утечках?",
    "options": [
      "Внизу, в колодцах, в подвалах.",
      "Вверху, под потолком.",
      "В вентиляционных системах.",
      "Выходит из сварочного ящика в верхние вентиляционные отверстия, быстро улетучивается, так как легче воздуха."
    ],
    "correct": 0
  },
  {
    "question": "Какой цвет наружной поверхности и надписи на баллоне с аммиаком?",
    "options": [
      "Белый, надпись красная «аммиак».",
      "Желтый, надпись черная «аммиак».",
      "Желтый, надпись красная «аммиак»."
    ],
    "correct": 1
  },
  {
    "question": "Как определяется наполнение баллонов газом?",
    "options": [
      "По манометру.",
      "Газоанализатором.",
      "Взвешиванием."
    ],
    "correct": 2
  },
  {
    "question": "Как правильно перемещать баллоны внутри помещения?",
    "options": [
      "На руках.",
      "На специальных носилках или кантовать в слегка наклонном положении.",
      "На плечах.",
      "Перекатывать в горизонтальном положении."
    ],
    "correct": 1
  },
  {
    "question": "Требуется ли оснащение складов для баллонов вентиляцией?",
    "options": [
      "Склады должны иметь естественную или искусственную вентиляцию.",
      "Вентиляция на складе не требуется.",
      "Склады должны иметь только искусственную вентиляцию."
    ],
    "correct": 0
  },
  {
    "question": "Разрешается ли совместное складское хранение порожних баллонов для горючих газов и кислорода?",
    "options": [
      "Разрешается.",
      "Разрешается у разных стен.",
      "Разрешается, если закреплены.",
      "Запрещается."
    ],
    "correct": 3
  },
  {
    "question": "Допускается ли устанавливать баллоны в проходах и проездах, в цокольных и подвальных помещениях?",
    "options": [
      "Допускается.",
      "Запрещается.",
      "С письменного распоряжения мастера",
      "Правильный ответ в пунктах 1, 3."
    ],
    "correct": 1
  },
  {
    "question": "Какой цвет наружной поверхности и надписи на баллоне с углекислотой?",
    "options": [
      "Черный, надпись красная «углекислота».",
      "Желтый, надпись черная «углекислота».",
      "Черный, надпись желтая «углекислота»."
    ],
    "correct": 2
  },
  {
    "question": "В каком случае боковой штуцер вентиля имеет левую резьбу?",
    "options": [
      "Для баллонов с негорючими газами.",
      "Для баллонов с горючими газами.",
      "Для баллонов с кислородом."
    ],
    "correct": 1
  },
  {
    "question": "Какие баллоны запрещается использовать?",
    "options": [
      "С неисправным вентилем.",
      "С повреждённым корпусом.",
      "Не имеющего чёткой окраски и надписи.",
      "С истёкшим сроком освидетельствования.",
      "Во всех случаях."
    ],
    "correct": 4
  },
  {
    "question": "Разрешается ли перевозка в одном контейнере порожних и наполненных баллонов?",
    "options": [
      "Запрещается.",
      "Разрешается не более 10 баллонов.",
      "Разрешается при обязательной их маркировке.",
      "Разрешается по письменному распоряжению инспекции."
    ],
    "correct": 2
  },
  {
    "question": "Где должны располагаться шкафы, в которых храниться более 10 баллонов?",
    "options": [
      "Внутри производственного помещения.",
      "В подвальном помещении.",
      "Снаружи производственных зданий у глухих несгораемых стен.",
      "На расстоянии не менее 1 м от окон и входных дверей."
    ],
    "correct": 2
  },
  {
    "question": "В какой цвет окрашивают баллон с азотом?",
    "options": [
      "В тёмно-зелёный цвет с красной надписью.",
      "В черный цвет с желтой надписью.",
      "В коричневый цвет с белой надписью.",
      "В желтый цвет с красной надписью."
    ],
    "correct": 1
  },
  {
    "question": "Через какой срок проводится очередная проверка знаний рабочих?",
    "options": [
      "1 раз в 12 месяцев.",
      "1 раз в 3 года.",
      "1 раз в 6 месяцев."
    ],
    "correct": 0
  },
  {
    "question": "Какое действие оказывает кислород на человека?",
    "options": [
      "Удушающее.",
      "Наркотическое.",
      "Вызывает отёк лёгких при дыхании свыше 30 минут.",
      "Вызывает заболевание почек и печени."
    ],
    "correct": 2
  },
  {
    "question": "Назовите физико химические свойства ацетилена.",
    "options": [
      "Газ без цвета, без запаха, не горит.",
      "Горючий газ легче воздуха, без цвета, без вкуса, с резким специфическим запахом без цвета, без вкуса.",
      "Газ без цвета, без запаха, горит, тяжелее воздуха.",
      "Газ, не горит, но поддерживает горение."
    ],
    "correct": 1
  },
  {
    "question": "Какую резьбу должен иметь боковой штуцер вентиля для баллона, наполненный  водородом:",
    "options": [
      "Правую резьбу.",
      "Левую резьбу."
    ],
    "correct": 1
  },
  {
    "question": "Чем проверяется герметичность вентиля?",
    "options": [
      "Огнём.",
      "Аммиаком.",
      "Мыльной эмульсией.",
      "Спиртом"
    ],
    "correct": 2
  },
  {
    "question": "Каким требованиям должно отвечать здание склада для хранения баллонов?",
    "options": [
      "Должно быть одноэтажным, с покрытиями легкого типа, без чердачных помещений.",
      "Стены, перегородки, покрытия склада должны быть из несгораемых материалов.",
      "Полы должны быть ровные с нескользкой поверхностью.",
      "Оконные стекла должны быть матовые или закрашены белой краской.",
      "Правильные ответы в п. 1, 2, 3 и 4."
    ],
    "correct": 4
  }
]